stacked_hourglass/__init__.py
stacked_hourglass/loss.py
stacked_hourglass/model.py
stacked_hourglass/predictor.py
stacked_hourglass/train.py
stacked_hourglass/datasets/__init__.py
stacked_hourglass/datasets/common.py
stacked_hourglass/datasets/mpii.py
stacked_hourglass/res/__init__.py
stacked_hourglass/res/detections_our_format.mat
stacked_hourglass/res/mpii_annotations.json.gz
stacked_hourglass/res/__pycache__/__init__.cpython-37.pyc
stacked_hourglass/utils/__init__.py
stacked_hourglass/utils/evaluation.py
stacked_hourglass/utils/finetune.py
stacked_hourglass/utils/imutils.py
stacked_hourglass/utils/logger.py
stacked_hourglass/utils/misc.py
stacked_hourglass/utils/pilutil.py
stacked_hourglass/utils/transforms.py
pytorch_stacked_hourglass-1.0.0a9.dist-info/LICENSE
pytorch_stacked_hourglass-1.0.0a9.dist-info/METADATA
pytorch_stacked_hourglass-1.0.0a9.dist-info/WHEEL
pytorch_stacked_hourglass-1.0.0a9.dist-info/top_level.txt
pytorch_stacked_hourglass-1.0.0a9.dist-info/RECORD
