Metadata-Version: 2.1
Name: pytorch-stacked-hourglass
Version: 1.0.0a9
Summary: UNKNOWN
Home-page: https://github.com/anibali/pytorch-stacked-hourglass
Maintainer: Aiden Nibali
License: UNKNOWN
Platform: UNKNOWN
Classifier: Topic :: Scientific/Engineering :: Image Recognition
Classifier: Intended Audience :: Science/Research
Classifier: Intended Audience :: Developers
Classifier: Programming Language :: Python :: 3
Classifier: License :: OSI Approved :: GNU General Public License v3 (GPLv3)
Classifier: Operating System :: OS Independent
Requires-Dist: importlib-resources
Requires-Dist: Pillow
Requires-Dist: scipy
Requires-Dist: tabulate
Requires-Dist: torch
